premod/__init__.py
premod/io.py
premod/parser_generic.py
premod/plot.py
premod/read_results.py
premod/solver.py
premod/strength.py
premod/default/alloy.txt
premod/default/phasesLib.txt
premod/default/pptmodels.txt
premod/default/precipitationTest.txt
premod/default/solver.txt
premod/default/temperature_history.txt
premod/default/test_default.txt
pypremod-0.1.5.dist-info/METADATA
pypremod-0.1.5.dist-info/WHEEL
pypremod-0.1.5.dist-info/top_level.txt
pypremod-0.1.5.dist-info/RECORD
